custom_libs/__init__.py
custom_libs/teamLists.py
nfl_stadiums/__init__.py
nfl_stadiums/nfl_stadiums.py
nfl_stadiums/stadiums.py
nfl_stadiums/calibrations/__init__.py
nfl_stadiums/calibrations/cals.py
nfl_stadiums/custom_libs/__init__.py
nfl_stadiums/custom_libs/teamLists.py
nfl_stadiums/custom_libs/wikipediaCal.py
nfl_stadiums-2.0.4.dist-info/LICENSE
nfl_stadiums-2.0.4.dist-info/METADATA
nfl_stadiums-2.0.4.dist-info/WHEEL
nfl_stadiums-2.0.4.dist-info/top_level.txt
nfl_stadiums-2.0.4.dist-info/RECORD
