Metadata-Version: 2.1
Name: nfl-stadiums
Version: 2.0.4
Summary: A simple python package that provides easy access to NFL stadium data
Home-page: https://github.com/lukhed/nfl_stadiums
Author: lukhed
Author-email: lukhed.mail@gmail.com
Classifier: Programming Language :: Python :: 3
Classifier: License :: OSI Approved :: MIT License
Classifier: Operating System :: OS Independent
Requires-Python: >=3.9
License-File: LICENSE
Requires-Dist: lukhed-basic-utils>=1.4.0
